wgtk/WireGuard.py
wgtk/__about__.py
wgtk/__init__.py
wgtk/__main__.py
wgtk/application.py
wgtk/configuration.py
wgtk/file.py
wgtk/network.py
wgtk/template/__init__.py
wgtk/template/install.bash
wgtk/template/network.yml
wgtk/template/start.bash
wgtk/template/stop.bash
wgtk/template/systemd.service
wireguard_toolkit-0.0.2.dist-info/METADATA
wireguard_toolkit-0.0.2.dist-info/WHEEL
wireguard_toolkit-0.0.2.dist-info/licenses/LICENSE
wireguard_toolkit-0.0.2.dist-info/RECORD
